dv_launcher/__init__.py
dv_launcher/main.py
dv_launcher/cli/__init__.py
dv_launcher/cli/config.py
dv_launcher/cli/db.py
dv_launcher/cli/deploy.py
dv_launcher/cli/init.py
dv_launcher/cli/version.py
dv_launcher/data/constants.py
dv_launcher/services/__init__.py
dv_launcher/services/database_creator.py
dv_launcher/services/database/__init__.py
dv_launcher/services/database/odoo.py
dv_launcher/services/database/postgres.py
dv_launcher/services/docker/__init__.py
dv_launcher/services/docker/compose.py
dv_launcher/services/files/addons.py
dv_launcher/services/files/file_operations.py
dv_launcher/services/files/traefik.py
dv_launcher/services/logging/custom_logger.py
dv_launcher/services/orchestration/__init__.py
dv_launcher/services/orchestration/deployment.py
dv_launcher-2.0.6.dist-info/METADATA
dv_launcher-2.0.6.dist-info/WHEEL
dv_launcher-2.0.6.dist-info/entry_points.txt
dv_launcher-2.0.6.dist-info/RECORD
