Metadata-Version: 2.4
Name: dv-launcher
Version: 2.0.6
Summary: Odoo deploy command line tool
Requires-Python: >=3.10.12
Requires-Dist: httpx>=0.28.1
Requires-Dist: psutil==7.1.3
Requires-Dist: python-dotenv==1.2.1
Requires-Dist: requests>=2.32.5
Requires-Dist: typer==0.21.1
